pyncaids/__init__.py
pyncaids/pyncaids.py
tests/__init__.py
tests/test_ncaids.py
pyncaids-0.0.1.dist-info/LICENSE
pyncaids-0.0.1.dist-info/METADATA
pyncaids-0.0.1.dist-info/WHEEL
pyncaids-0.0.1.dist-info/top_level.txt
pyncaids-0.0.1.dist-info/RECORD
