Metadata-Version: 2.1
Name: pyncaids
Version: 0.0.1
Summary: National Competent Authority (NCA) Identifiers as a Python module
Home-page: https://github.com/badmetacoder/pyncaids
Author: Jacek Artymiak
Author-email: jacek@artymiak.com
License: UNKNOWN
Platform: UNKNOWN
Classifier: Programming Language :: Python :: 3.7
Classifier: License :: OSI Approved :: BSD License
Classifier: Operating System :: OS Independent
Classifier: Development Status :: 5 - Production/Stable
Classifier: Intended Audience :: Financial and Insurance Industry
Classifier: Topic :: Office/Business :: Financial
Classifier: Natural Language :: English
Requires-Python: >=3.7
